Workbook

Sheet Dashboard
B2: Dashboard de Ejecución — Plan de Pruebas PS-01 a PS-65
B5: Total de casos | D5: Ejecutados | F5: Aprobados | H5: Fallidos
B6: =COUNTA(Hoja1!A2:A66) -> 65 | D6: =COUNTIF(Hoja1!$I$2:$I$66,"Aprobado")+COUNTIF(Hoja1!$I$2:$I$66,"Fallido") -> 0 | F6: =COUNTIF(Hoja1!$I$2:$I$66,"Aprobado") -> 0 | H6: =COUNTIF(Hoja1!$I$2:$I$66,"Fallido") -> 0
B8: % Avance | D8: % Aprobación (sobre ejecutados)
B9: =IFERROR((COUNTIF(Hoja1!$I$2:$I$66,"Aprobado")+COUNTIF(Hoja1!$I$2:$I$66,"Fallido"))/COUNTA(Hoja1!A2:A66),0) -> 0 | D9: =IFERROR(COUNTIF(Hoja1!$I$2:$I$66,"Aprobado")/(COUNTIF(Hoja1!$I$2:$I$66,"Aprobado")+COUNTIF(Hoja1!$I$2:$I$66,"Fallido")),0) -> 0
B11: Resumen por estado
B12: Estado | C12: Cantidad
B13: Aprobado | C13: =COUNTIF(Hoja1!$I$2:$I$66,"Aprobado") -> 0
B14: Fallido | C14: =COUNTIF(Hoja1!$I$2:$I$66,"Fallido") -> 0
B15: Pendiente | C15: =COUNTA(Hoja1!A2:A66)-COUNTIF(Hoja1!$I$2:$I$66,"Aprobado")-COUNTIF(Hoja1!$I$2:$I$66,"Fallido") -> 65
B17: Avance por requisito (CU)
B18: CU | C18: Aprobado | D18: Fallido | E18: Pendiente | F18: Total
B19: CU-01 | C19: =COUNTIFS(Hoja1!$C$2:$C$66,"CU-01",Hoja1!$I$2:$I$66,"Aprobado") -> 0 | D19: =COUNTIFS(Hoja1!$C$2:$C$66,"CU-01",Hoja1!$I$2:$I$66,"Fallido") -> 0 | E19: =F19-C19-D19 -> 12 | F19: =COUNTIF(Hoja1!$C$2:$C$66,"CU-01") -> 12
B20: CU-02 | C20: =COUNTIFS(Hoja1!$C$2:$C$66,"CU-02",Hoja1!$I$2:$I$66,"Aprobado") -> 0 | D20: =COUNTIFS(Hoja1!$C$2:$C$66,"CU-02",Hoja1!$I$2:$I$66,"Fallido") -> 0 | E20: =F20-C20-D20 -> 8 | F20: =COUNTIF(Hoja1!$C$2:$C$66,"CU-02") -> 8
B21: CU-03 | C21: =COUNTIFS(Hoja1!$C$2:$C$66,"CU-03",Hoja1!$I$2:$I$66,"Aprobado") -> 0 | D21: =COUNTIFS(Hoja1!$C$2:$C$66,"CU-03",Hoja1!$I$2:$I$66,"Fallido") -> 0 | E21: =F21-C21-D21 -> 7 | F21: =COUNTIF(Hoja1!$C$2:$C$66,"CU-03") -> 7
B22: CU-04 | C22: =COUNTIFS(Hoja1!$C$2:$C$66,"CU-04",Hoja1!$I$2:$I$66,"Aprobado") -> 0 | D22: =COUNTIFS(Hoja1!$C$2:$C$66,"CU-04",Hoja1!$I$2:$I$66,"Fallido") -> 0 | E22: =F22-C22-D22 -> 6 | F22: =COUNTIF(Hoja1!$C$2:$C$66,"CU-04") -> 6
B23: CU-05 | C23: =COUNTIFS(Hoja1!$C$2:$C$66,"CU-05",Hoja1!$I$2:$I$66,"Aprobado") -> 0 | D23: =COUNTIFS(Hoja1!$C$2:$C$66,"CU-05",Hoja1!$I$2:$I$66,"Fallido") -> 0 | E23: =F23-C23-D23 -> 8 | F23: =COUNTIF(Hoja1!$C$2:$C$66,"CU-05") -> 8
B24: CU-06 | C24: =COUNTIFS(Hoja1!$C$2:$C$66,"CU-06",Hoja1!$I$2:$I$66,"Aprobado") -> 0 | D24: =COUNTIFS(Hoja1!$C$2:$C$66,"CU-06",Hoja1!$I$2:$I$66,"Fallido") -> 0 | E24: =F24-C24-D24 -> 9 | F24: =COUNTIF(Hoja1!$C$2:$C$66,"CU-06") -> 9
B25: CU-WEB | C25: =COUNTIFS(Hoja1!$C$2:$C$66,"CU-WEB",Hoja1!$I$2:$I$66,"Aprobado") -> 0 | D25: =COUNTIFS(Hoja1!$C$2:$C$66,"CU-WEB",Hoja1!$I$2:$I$66,"Fallido") -> 0 | E25: =F25-C25-D25 -> 15 | F25: =COUNTIF(Hoja1!$C$2:$C$66,"CU-WEB") -> 15

Sheet Hoja1
A1: ID Prueba | B1: Nombre de la Prueba | C1: Requisito (CU) | D1: Precondición | E1: Datos | F1: Acción | G1: Resultado esperado | H1: Resultado obtenido | I1: Criterio de aceptación | J1: Evidencia
A2: PS-01 | B2: Login correcto (Recepcionista) | C2: CU-06 | D2: Usuario activo | E2: Correo: rep@hotel.cl / Clave: "1234" | F2: Enviar POST a /login | G2: Retorna Token JWT y rol RECEPCIONISTA
A3: PS-02 | B3: Login correcto (Limpieza) | C3: CU-06 | D3: Usuario activo | E3: Correo: aseo@hotel.cl / Clave: "1234" | F3: Enviar POST a /login | G3: Retorna Token JWT y rol LIMPIEZA
A4: PS-03 | B4: Login con clave incorrecta | C4: CU-06 | D4: Usuario registrado | E4: Correo: rep@hotel.cl / Clave: "mal" | F4: Enviar POST a /login | G4: Rechazo. No genera Token. Muestra error (401)
A5: PS-04 | B5: Login con campos vacíos | C5: CU-06 | D5: Ninguna | E5: Correo: "" / Clave: "" | F5: Enviar POST a /login | G5: Validación de backend rechaza por campos nulos
A6: PS-05 | B6: Intento de Inyección SQL | C6: CU-06 | D6: Ninguna | E6: Correo: "admin' OR 1=1--" | F6: Enviar POST a /login | G6: ORM escapa caracteres, login fallido (401)
A7: PS-06 | B7: Acceso sin Token (Ruta protegida) | C7: CU-01 | D7: Usuario no logueado | E7: Sin Header Authorization | F7: Hacer GET a /habitaciones | G7: Middleware bloquea acceso (403 Forbidden)
A8: PS-07 | B8: Expiración de Token JWT | C8: CU-06 | D8: Token vencido (más de 8 horas) | E8: Token viejo | F8: Hacer GET a /habitaciones | G8: Middleware detecta expiración y desloguea
A9: PS-08 | B9: Control de Roles (RBAC) - Denegado | C9: CU-06 | D9: Mucama logueada (Rol LIMPIEZA) | E9: Token de limpieza | F9: Intentar hacer POST a /pagos | G9: Bloqueo por falta de privilegios (403)
A10: PS-09 | B10: Login con usuario inactivo | C10: CU-06 | D10: Usuario dado de baja en BD | E10: Correo: ex@hotel.cl | F10: Enviar POST a /login | G10: Rechazo por cuenta inactiva (403 Forbidden)
A11: PS-10 | B11: Solicitud de recuperación de clave | C11: CU-06 | D11: Usuario registrado | E11: Correo: rep@hotel.cl | F11: Clic en "Olvidé mi contraseña" | G11: Sistema envía correo con link temporal
A12: PS-11 | B12: Consultar disponibilidad (Fechas válidas) | C12: CU-01 | D12: Recepcionista logueado | E12: Inicio: Hoy / Fin: Mañana | F12: Enviar GET a /disponibilidad | G12: Retorna lista de habitaciones libres/ocupadas
A13: PS-12 | B13: Consultar sin fechas (Por defecto) | C13: CU-01 | D13: Recepcionista logueado | E13: Vacío | F13: Enviar GET a /disponibilidad | G13: Asume fecha de hoy y muestra estado actual
... A66: PS-65 | B66: Descargar factura antigua desde web | C66: CU-WEB | D66: Huésped logueado | E66: Clic en ícono de PDF de reserva pasada | F66: Sistema descarga el archivo usando el GeneradorFactory | G66: Sistema descarga el archivo (GeneradorFactory)
